moysklad/__init__.py
moysklad/__version__.py
moysklad/api.py
moysklad/exceptions.py
moysklad/queries.py
moysklad/urls.py
moysklad/utils.py
moysklad/http/__init__.py
moysklad/http/client.py
moysklad/http/utils.py
fs_moysklad_api-0.5.0.dist-info/LICENSE
fs_moysklad_api-0.5.0.dist-info/METADATA
fs_moysklad_api-0.5.0.dist-info/WHEEL
fs_moysklad_api-0.5.0.dist-info/top_level.txt
fs_moysklad_api-0.5.0.dist-info/RECORD
