Metadata-Version: 2.1
Name: fs-moysklad-api
Version: 0.5.0
Summary: MoySklad API wrapper
Home-page: https://github.com/fogstream/fs-moysklad
Maintainer: fadedDexofan
Maintainer-email: fadeddexofan@gmail.com
License: MIT
Keywords: moysklad,api,fs-moysklad-api,sdk,integration,fogstream,lib
Platform: UNKNOWN
Classifier: License :: OSI Approved :: MIT License
Classifier: Development Status :: 5 - Production/Stable
Classifier: Intended Audience :: Developers
Classifier: Operating System :: Unix
Classifier: Topic :: Software Development :: Libraries
Classifier: Programming Language :: Python :: 3
Classifier: Programming Language :: Python :: 3.6
Classifier: Programming Language :: Python :: 3.7
Classifier: Programming Language :: Python :: Implementation :: CPython
Requires-Python: >=3.6.0
Requires-Dist: requests
Provides-Extra: proxy
Requires-Dist: PySocks ; extra == 'proxy'
